ovsegmentation/__init__.py
ovsegmentation/ovsegmentation.py
ovsegmentation/knowledge_mapping/processors/__init__.py
ovsegmentation/knowledge_mapping/processors/detector.py
ovsegmentation/knowledge_mapping/processors/detector_models.py
ovsegmentation/knowledge_mapping/processors/grounding.py
ovsegmentation/knowledge_mapping/processors/ovsegmentation.py
ovsegmentation/knowledge_mapping/processors/sam.py
ovsegmentation/knowledge_mapping/processors/sam_models.py
ovsegmentation/knowledge_mapping/processors/types.py
ovsegmentation/knowledge_mapping/processors/utils.py
ovsegmentation/knowledge_mapping/third_party/README.md
ovsegmentation/knowledge_mapping/third_party/GroundingDINO/groundingdino/__init__.py
ovsegmentation/knowledge_mapping/third_party/GroundingDINO/groundingdino/version.py
ovsegmentation/knowledge_mapping/third_party/GroundingDINO/groundingdino/config/GroundingDINO_SwinB_cfg.py
ovsegmentation/knowledge_mapping/third_party/GroundingDINO/groundingdino/config/GroundingDINO_SwinT_OGC.py
ovsegmentation/knowledge_mapping/third_party/GroundingDINO/groundingdino/config/__init__.py
ovsegmentation/knowledge_mapping/third_party/GroundingDINO/groundingdino/datasets/__init__.py
ovsegmentation/knowledge_mapping/third_party/GroundingDINO/groundingdino/datasets/transforms.py
ovsegmentation/knowledge_mapping/third_party/GroundingDINO/groundingdino/models/__init__.py
ovsegmentation/knowledge_mapping/third_party/GroundingDINO/groundingdino/models/registry.py
ovsegmentation/knowledge_mapping/third_party/GroundingDINO/groundingdino/models/GroundingDINO/__init__.py
ovsegmentation/knowledge_mapping/third_party/GroundingDINO/groundingdino/models/GroundingDINO/bertwarper.py
ovsegmentation/knowledge_mapping/third_party/GroundingDINO/groundingdino/models/GroundingDINO/fuse_modules.py
ovsegmentation/knowledge_mapping/third_party/GroundingDINO/groundingdino/models/GroundingDINO/groundingdino.py
ovsegmentation-1.0.41.dist-info/LICENSE
ovsegmentation-1.0.41.dist-info/METADATA
ovsegmentation-1.0.41.dist-info/WHEEL
ovsegmentation-1.0.41.dist-info/top_level.txt
ovsegmentation-1.0.41.dist-info/RECORD
