Metadata-Version: 2.1
Name: ovsegmentation
Version: 1.0.41
Summary: Open vocabulary detection and segmentation package
Author: Ilya Obrubov
License: Apache License
License-File: LICENSE
Requires-Dist: pip <=22.0.2
Requires-Dist: transformers <=4.42.3
Requires-Dist: timm <=1.0.7
Requires-Dist: addict
Requires-Dist: yapf
Requires-Dist: numpy <=1.26.4
Requires-Dist: opencv-python
Requires-Dist: opencv-python-headless
Requires-Dist: supervision
Requires-Dist: pycocotools
Requires-Dist: torch ==2.3.1
Requires-Dist: torchpack ==0.3.1
Requires-Dist: torchvision ==0.18.1
Requires-Dist: open3d
Requires-Dist: pillow
Requires-Dist: matplotlib
Requires-Dist: werkzeug ==3.0.3
Requires-Dist: flask ==3.0.3
Requires-Dist: tensorrt ==8.6.1.post1
Requires-Dist: onnxsim
Requires-Dist: onnxruntime <=1.18.1
